penguin_analyst_boaz/__init__.py
penguin_analyst_boaz-0.1.2.dist-info/METADATA
penguin_analyst_boaz-0.1.2.dist-info/WHEEL
penguin_analyst_boaz-0.1.2.dist-info/RECORD
