Metadata-Version: 2.1
Name: penguin-analyst-boaz
Version: 0.1.2
Summary: 
Author: Boaz
Author-email: boazbokek@gmail.com
Requires-Python: >=3.8,<4.0
Classifier: Programming Language :: Python :: 3
Classifier: Programming Language :: Python :: 3.8
Classifier: Programming Language :: Python :: 3.9
Classifier: Programming Language :: Python :: 3.10
Classifier: Programming Language :: Python :: 3.11
Requires-Dist: pandas (>=1.3.5,<2.0.0)
